{
  "timestamp": 1767384668089,
  "savedAt": "2026-01-02T20:11:08.089Z",
  "stepName": "step_7_style_analysis",
  "response": {
    "brandVisualDNA": {
      "primaryColors": [
        {
          "hex": "#1A1A1A",
          "name": "Charcoal Black",
          "usage": "text"
        },
        {
          "hex": "#FFFFFF",
          "name": "Pure White",
          "usage": "backgrounds"
        },
        {
          "hex": "#FFD700",
          "name": "Golden Yellow",
          "usage": "accents/highlights"
        }
      ],
      "secondaryColors": [
        {
          "hex": "#E5E5E5",
          "name": "Light Gray",
          "usage": "borders"
        },
        {
          "hex": "#B22222",
          "name": "Fire Brick Red",
          "usage": "highlights"
        }
      ],
      "colorPaletteNotes": "Primary use of black and white for a clean look, with occasional splashes of gold and red for emphasis",
      "typography": {
        "headlineStyle": "bold",
        "preferredFonts": [
          "Montserrat",
          "Open Sans",
          "Roboto"
        ],
        "textPlacement": "centered",
        "textShadow": false,
        "textBackgroundBox": false
      },
      "composition": {
        "primaryStyle": "minimalist",
        "whitespaceUsage": "heavy",
        "gridPattern": "centered",
        "borderStyle": "thin-white"
      },
      "lighting": {
        "primaryStyle": "soft",
        "contrast": "medium",
        "saturation": "muted"
      },
      "islamicElements": {
        "useGeometricPatterns": false,
        "patternStyle": "subtle",
        "frequencyOfIslamicMotifs": "occasionally"
      },
      "imageStyle": {
        "realism": "photorealistic",
        "subjects": "objects and abstract",
        "faceless": true,
        "backgroundStyle": "solid-color",
        "moodBoard": [
          "modern",
          "clean",
          "elegant",
          "minimalist",
          "professional"
        ]
      },
      "contentTypeStyles": {
        "reels": {
          "openingFrame": "question",
          "transitionStyle": "fade",
          "textAnimations": "fade-in"
        },
        "carousels": {
          "slideCount": "5-10 slides",
          "slideFlow": "story-based",
          "coverSlideStyle": "bold-headline"
        },
        "singleImages": {
          "preferredFormat": "quote-card",
          "textOverlayUsage": "always"
        }
      }
    },
    "aiImagePromptModifiers": {
      "styleKeywords": [
        "modern",
        "minimalist",
        "elegant",
        "clean",
        "professional"
      ],
      "qualityModifiers": [
        "professional",
        "high detail",
        "instagram-ready"
      ],
      "avoidKeywords": [
        "faces",
        "chaotic",
        "cluttered"
      ],
      "aspectRatioPreferences": {
        "reels": "9:16",
        "carousels": "1:1",
        "posts": "1:1"
      }
    },
    "examplePromptTemplate": "Create a modern, minimalist Instagram post with a clean, photorealistic style. Use Charcoal Black text on a Pure White background, with Golden Yellow accents. The composition is centered and features heavy whitespace. Include a bold headline in Montserrat font, with no text shadow or background box. The mood is elegant and professional, and the aspect ratio is 1:1 for carousel posts."
  }
}